pytest_req/__init__.py
pytest_req/assertions.py
pytest_req/config.py
pytest_req/log.py
pytest_req/plugin.py
pytest_req/utils/__init__.py
pytest_req/utils/diff.py
pytest_req/utils/jmespath.py
pytest_req-0.5.2.dist-info/METADATA
pytest_req-0.5.2.dist-info/WHEEL
pytest_req-0.5.2.dist-info/entry_points.txt
pytest_req-0.5.2.dist-info/licenses/LICENSE
pytest_req-0.5.2.dist-info/RECORD
