Metadata-Version: 2.4
Name: pytest-req
Version: 0.5.2
Summary: pytest requests plugin
License: Apache-2.0
License-File: LICENSE
Author: bugmaster
Author-email: defnngj@gmail.com
Requires-Python: >=3.9
Classifier: Development Status :: 5 - Production/Stable
Classifier: Framework :: Pytest
Classifier: Intended Audience :: Developers
Classifier: License :: OSI Approved :: Apache Software License
Classifier: Programming Language :: Python :: 3
Classifier: Programming Language :: Python :: 3.9
Classifier: Programming Language :: Python :: 3.10
Classifier: Programming Language :: Python :: 3.11
Classifier: Programming Language :: Python :: 3.12
Classifier: Programming Language :: Python :: 3.13
Classifier: Topic :: Software Development :: Testing
Requires-Dist: jmespath (>=1.0.1)
Requires-Dist: loguru (>=0.7.2)
Requires-Dist: pytest (>=8.4.2)
Requires-Dist: pytest-base-url (>=2.1.0)
Requires-Dist: requests (>=2.32.3)
Project-URL: Homepage, https://github.com/seldomqa/pytest-req
Project-URL: Repository, https://github.com/seldomqa/pytest-req
